Metadata-Version: 2.1
Name: image2gps
Version: 1.3.0
Summary: Extract time and coords from image 🖼📍⏱️
Home-page: https://github.com/abionics/image2gps
Author: Alex Ermolaev
Author-email: abionics.dev@gmail.com
License: MIT
Keywords: image gps location extract exif
Classifier: Intended Audience :: Developers
Classifier: Intended Audience :: Science/Research
Classifier: License :: OSI Approved :: MIT License
Classifier: Operating System :: OS Independent
Classifier: Programming Language :: Python :: 3
Classifier: Programming Language :: Python :: 3.10
Classifier: Programming Language :: Python :: 3.11
Classifier: Topic :: Scientific/Engineering :: GIS
Classifier: Topic :: Scientific/Engineering :: Image Processing
Classifier: Topic :: Software Development :: Libraries :: Python Modules
Classifier: Typing :: Typed
License-File: LICENSE.txt
